odoo9_addon_product_supplier_code_purchase-9.0.1.0.0-py2.7-nspkg.pth
odoo9_addon_product_supplier_code_purchase-9.0.1.0.0.dist-info/DESCRIPTION.rst
odoo9_addon_product_supplier_code_purchase-9.0.1.0.0.dist-info/METADATA
odoo9_addon_product_supplier_code_purchase-9.0.1.0.0.dist-info/RECORD
odoo9_addon_product_supplier_code_purchase-9.0.1.0.0.dist-info/WHEEL
odoo9_addon_product_supplier_code_purchase-9.0.1.0.0.dist-info/metadata.json
odoo9_addon_product_supplier_code_purchase-9.0.1.0.0.dist-info/namespace_packages.txt
odoo9_addon_product_supplier_code_purchase-9.0.1.0.0.dist-info/top_level.txt
odoo_addons/product_supplier_code_purchase/README.rst
odoo_addons/product_supplier_code_purchase/__init__.py
odoo_addons/product_supplier_code_purchase/__openerp__.py
odoo_addons/product_supplier_code_purchase/models/__init__.py
odoo_addons/product_supplier_code_purchase/models/purchase_order.py
odoo_addons/product_supplier_code_purchase/views/purchase_order_view.xml
